[
  {
    "name":"U.S.",
    "series_id":"PET.EMM_EPMR_PTE_NUS_DPG.W",
    "full_name":"U.S.",
    "name_id":"US",
    "id":1
  },
  {
    "name":"East Coast",
    "series_id":"PET.EMM_EPMR_PTE_R10_DPG.W",
    "full_name":"East Coast (PADD1)",
    "name_id":"EC",
    "id":2
  },
  {
    "name":"New England",
    "series_id":"PET.EMM_EPMR_PTE_R1X_DPG.W",
    "full_name":"New England (PADD1A)",
    "name_id":"NE",
    "id":3
  },
  {
    "name":"Central Atlantic",
    "series_id":"PET.EMM_EPMR_PTE_R1Y_DPG.W",
    "full_name":"Central Atlantic (PADD1B)",
    "name_id":"CAT",
    "id":4
  },
  {
    "name":"Lower Atlantic",
    "series_id":"PET.EMM_EPMR_PTE_R1Z_DPG.W",
    "full_name":"Lower Atlantic (PADD1C)",
    "name_id":"LAT",
    "id":5
  },
  {
    "name":"Midwest",
    "series_id":"PET.EMM_EPMR_PTE_R20_DPG.W",
    "full_name":"Midwest (PADD2)",
    "name_id":"MW",
    "id":6
  },
  {
    "name":"Gulf Coast",
    "series_id":"PET.EMM_EPMR_PTE_R30_DPG.W",
    "full_name":"Gulf Coast (PADD3)",
    "name_id":"GC",
    "id":7
  },
  {
    "name":"Rocky Mountain",
    "series_id":"PET.EMM_EPMR_PTE_R40_DPG.W",
    "full_name":"Rocky Mountain (PADD4)",
    "name_id":"RM",
    "id":8
  },
  {
    "name":"West Coast",
    "series_id":"PET.EMM_EPMR_PTE_R50_DPG.W",
    "full_name":"West Coast (PADD5)",
    "name_id":"WC",
    "id":9
  },
  {
    "name":"West Coast less California",
    "series_id":"PET.EMM_EPMR_PTE_R5XCA_DPG.W",
    "full_name":"West Coast less California",
    "name_id":"WCLC",
    "id":10
  },
  {
    "name":"California",
    "series_id":"PET.EMM_EPMR_PTE_SCA_DPG.W",
    "full_name":"California",
    "name_id":"CA",
    "id":11
  },
  {
    "name":"Colorado",
    "series_id":"PET.EMM_EPMR_PTE_SCO_DPG.W",
    "full_name":"Colorado",
    "name_id":"CO",
    "id":12
  },
  {
    "name":"Florida",
    "series_id":"PET.EMM_EPMR_PTE_SFL_DPG.W",
    "full_name":"Florida",
    "name_id":"FL",
    "id":13
  },
  {
    "name":"Massachusetts",
    "series_id":"PET.EMM_EPMR_PTE_SMA_DPG.W",
    "full_name":"Massachusetts",
    "name_id":"MA",
    "id":14
  },
  {
    "name":"Minnesota",
    "series_id":"PET.EMM_EPMR_PTE_SMN_DPG.W",
    "full_name":"Minnesota",
    "name_id":"MN",
    "id":15
  },
  {
    "name":"New York",
    "series_id":"PET.EMM_EPMR_PTE_SNY_DPG.W",
    "full_name":"New York",
    "name_id":"NY",
    "id":16
  },
  {
    "name":"Ohio",
    "series_id":"PET.EMM_EPMR_PTE_SOH_DPG.W",
    "full_name":"Ohio",
    "name_id":"OH",
    "id":17
  },
  {
    "name":"Texas",
    "series_id":"PET.EMM_EPMR_PTE_STX_DPG.W",
    "full_name":"Texas",
    "name_id":"TX",
    "id":18
  },
  {
    "name":"Washington",
    "series_id":"PET.EMM_EPMR_PTE_SWA_DPG.W",
    "full_name":"Washington",
    "name_id":"WA",
    "id":19
  }
]